pyf.aggregator-1.0.0.dev0-py3.7-nspkg.pth
pyf/aggregator/__init__.py
pyf/aggregator/config.py
pyf/aggregator/fetcher.py
pyf/aggregator/indexer.py
pyf/aggregator/logger.py
pyf/aggregator/main.py
pyf.aggregator-1.0.0.dev0.dist-info/AUTHORS.rst
pyf.aggregator-1.0.0.dev0.dist-info/LICENSE
pyf.aggregator-1.0.0.dev0.dist-info/METADATA
pyf.aggregator-1.0.0.dev0.dist-info/WHEEL
pyf.aggregator-1.0.0.dev0.dist-info/entry_points.txt
pyf.aggregator-1.0.0.dev0.dist-info/namespace_packages.txt
pyf.aggregator-1.0.0.dev0.dist-info/top_level.txt
pyf.aggregator-1.0.0.dev0.dist-info/RECORD
