Metadata-Version: 2.1
Name: pyf.aggregator
Version: 1.0.0.dev0
Summary: Python Package Filter Aggregator
Home-page: https://pypi.python.org/pypi/pyf.aggregator
Author: 
Author-email: 
License: GNU General Public License v2 (GPLv2)
Platform: UNKNOWN
Classifier: Framework :: Pyramid
Classifier: Intended Audience :: Developers
Classifier: License :: OSI Approved :: Apache Software License
Classifier: Operating System :: OS Independent
Classifier: Programming Language :: Python
Classifier: Programming Language :: Python :: 3.6
Classifier: Programming Language :: Python :: 3.7
Requires-Dist: elasticsearch-dsl
Requires-Dist: lxml
Requires-Dist: requests
Requires-Dist: setuptools
Provides-Extra: dev
Requires-Dist: pdbpp ; extra == 'dev'
Provides-Extra: testing
Requires-Dist: responses ; extra == 'testing'
Requires-Dist: webtest ; extra == 'testing'
Requires-Dist: pytest ; extra == 'testing'
Requires-Dist: pytest-cov ; extra == 'testing'
